gen_tso/__init__.py
gen_tso/__main__.py
gen_tso/app_utils.py
gen_tso/export_script.py
gen_tso/gen_tso_app.py
gen_tso/utils.py
gen_tso/version.py
gen_tso/viewer_popovers.py
gen_tso/catalogs/__init__.py
gen_tso/catalogs/catalogs.py
gen_tso/catalogs/fetch_catalogs.py
gen_tso/catalogs/fetch_programs.py
gen_tso/catalogs/target.py
gen_tso/catalogs/utils.py
gen_tso/custom_shiny/__init__.py
gen_tso/custom_shiny/custom_shiny.py
gen_tso/data/base_theme.css
gen_tso/data/flux_rates_miri.pickle
gen_tso/data/flux_rates_nircam.pickle
gen_tso/data/flux_rates_niriss.pickle
gen_tso/data/flux_rates_nirspec.pickle
gen_tso/data/last_updated_nea.txt
gen_tso/data/last_updated_trexolist.txt
gen_tso/data/nea_data.txt
gen_tso/data/target_aliases.txt
gen_tso/data/tess_data.txt
gen_tso/data/trexolists.csv
gen_tso/data/user_planet_data.txt
gen_tso/data/images/gen_tso_logo.png
gen_tso/data/models/.gitignore
gen_tso/data/models/eclipse/.gitignore
gen_tso/data/models/sed/.gitignore
gen_tso/data/models/transit/.gitignore
gen_tso/data/programs/jwst_tso_programs.csv
gen_tso/data/programs/planets_per_program.json
gen_tso/data/throughputs/throughputs_miri_imaging_ts.pickle
gen_tso/data/throughputs/throughputs_miri_lrsslit.pickle
gen_tso/data/throughputs/throughputs_miri_lrsslitless.pickle
gen_tso/data/throughputs/throughputs_miri_mrs_ts.pickle
gen_tso/data/throughputs/throughputs_miri_target_acq.pickle
gen_tso/data/throughputs/throughputs_nircam_lw_ts.pickle
gen_tso/data/throughputs/throughputs_nircam_lw_tsgrism.pickle
gen_tso/data/throughputs/throughputs_nircam_sw_ts.pickle
gen_tso/data/throughputs/throughputs_nircam_sw_tsgrism.pickle
gen_tso/data/throughputs/throughputs_nircam_target_acq.pickle
gen_tso/data/throughputs/throughputs_niriss_soss.pickle
gen_tso/data/throughputs/throughputs_niriss_target_acq.pickle
gen_tso/data/throughputs/throughputs_nirspec_bots.pickle
gen_tso/data/throughputs/throughputs_nirspec_target_acq.pickle
gen_tso/pandeia_io/__init__.py
gen_tso/pandeia_io/pandeia_calculation.py
gen_tso-1.3.2.dist-info/licenses/LICENSE
gen_tso-1.3.2.dist-info/METADATA
gen_tso-1.3.2.dist-info/WHEEL
gen_tso-1.3.2.dist-info/entry_points.txt
gen_tso-1.3.2.dist-info/top_level.txt
gen_tso-1.3.2.dist-info/RECORD
