Metadata-Version: 2.4
Name: gen_tso
Version: 1.3.2
Summary: A general ETC for time-series observations
Author-email: Patricio Cubillos <pcubillos@fulbrightmail.org>
License-Expression: GPL-2.0-or-later
Project-URL: Homepage, https://github.com/pcubillos/gen_tso
Requires-Python: >=3.9
License-File: LICENSE
Requires-Dist: shiny>=1.0.0
Requires-Dist: pandeia.engine>=2025.7
Requires-Dist: scipy>=1.14.1
Requires-Dist: numpy>=2.0
Requires-Dist: requests>=2.19.1
Requires-Dist: astropy>=5.3.0
Requires-Dist: astroquery>=0.4.8
Requires-Dist: pandas
Requires-Dist: plotly
Requires-Dist: shinywidgets
Requires-Dist: faicons
Requires-Dist: prompt_toolkit>=3.0.0
Requires-Dist: pyratbay>=2.0.0.b3
Dynamic: license-file
